{
  "items": [
    {
      "id": "---",
      "date": "2026-01-19",
      "time": "第二場",
      "place": "崇仁廳",
      "content": "半圓A款1對(香檳)\nB款1對(香檳)",
      "note": "吳被祝",
      "buyer": "喬",
      "printed": true,
      "photoReturned": true,
      "group": "二殯組",
      "image": ""
    },
    {
      "id": "---",
      "date": "",
      "time": "",
      "place": "",
      "content": "",
      "note": "",
      "buyer": "",
      "printed": false,
      "photoReturned": false,
      "group": "板殯組",
      "image": ""
    }
  ]
}